rjm/__init__.py
rjm/entries.py
rjm/templates.py
rjm-1.4.0.dist-info/LICENSE
rjm-1.4.0.dist-info/WHEEL
rjm-1.4.0.dist-info/METADATA
rjm-1.4.0.dist-info/RECORD
