Metadata-Version: 2.1
Name: rjm
Version: 1.4.0
Summary: Python module for creating and reading journal files for Autodesk Revit.
Home-page: https://github.com/eirannejad/Revit-Journal-Maker
License: UNKNOWN
Author: Ehsan Iran-Nejad
Author-email: eirannejad@gmail.com
Classifier: License :: OSI Approved :: MIT License
